{"type": "FeatureCollection", "features": [{"type": "Feature", "geometry": {"type": "Point", "coordinates": [34.020882, -6.84165]}, "properties": {"city": "Rabat"}}, {"type": "Feature", "geometry": {"type": "Point", "coordinates": [-33.918861, 18.4233]}, "properties": {"city": "Cape Town"}}, {"type": "Feature", "geometry": {"type": "Point", "coordinates": [2.033632, 45.335855]}, "properties": {"city": "Mogadishu"}}]}